src/b_filter.v
module b_filter #(
    parameter CN = 4
) (
    input   clk,
    input   in_b,
    input   rst,
    output  reg out_b,
    output  im_out_b
);

reg [CN - 1 : 0]    count   = 0;
reg [CN - 1:0]      syn     = 0;

always @(posedge clk) begin
    if (~rst) begin
        syn <= 0;
    end else begin
        syn <= {syn[CN-2:0],in_b};

        if(&syn)begin
            out_b <= 1;
        end
        else begin
            out_b <= 0;
        end
        
    end

end

assign im_out_b = (~syn[CN - 1] & syn[CN - 2]) ? 1 : 0;

/*
    if (syn[2] == 0 and syn[1] == 1) begin
        im_out_b <= 1;
    end
    else begin
        im_out_b <= 0;
    end
always @(posedge clk or negedge rst) begin
    if (~rst) begin

        count       <= 0;
        out_b       <= 0;
        im_out_b    <= 0;

    end else begin
        
        if (in_b) begin
            
            count <= count + 1;
            
            if (count == {CN{1'b1}} ) begin

                im_out_b    <= 1;
                out_b       <= 1;
                            
            end
            else begin
                im_out_b    <= 0;
            end
            
        end

        else begin

            count <= 0;
            out_b <= 0;

        end

    end
end
  */  
endmodule

src/tb_b_filter.v
`timescale 1ns / 1ps

module tb_b_filter();
    
reg in_b = 0;
reg rst;
reg clk = 0;
wire out_b,im_out_b;

always #10 begin
    clk <= ~clk;
end


b_filter f1(
      .clk(clk),
      .in_b(in_b),
      .rst(rst),
      .out_b(out_b),
      .im_out_b(im_out_b)
);

initial begin
    $dumpfile("tb_b_filter.vcd");
    $dumpvars(0, tb_b_filter);
#10;
rst = 0;
#10;
rst = 1;
#100;
in_b <= 1;
#500;
in_b <= 0;

#1000;
$finish;
end

endmodule

tb_b_filter.vcd
$date
	Fri Mar 06 22:22:13 2026
$end
$version
	Icarus Verilog
$end
$timescale
	1ps
$end
$scope module tb_b_filter $end
$var wire 1 ! out_b $end
$var wire 1 " im_out_b $end
$var reg 1 # clk $end
$var reg 1 $ in_b $end
$var reg 1 % rst $end
$scope module f1 $end
$var wire 1 # clk $end
$var wire 1 $ in_b $end
$var wire 1 % rst $end
$var wire 1 " im_out_b $end
$var parameter 32 & CN $end
$var reg 4 ' count [3:0] $end
$var reg 1 ! out_b $end
$var reg 4 ( syn [3:0] $end
$upscope $end
$upscope $end
$enddefinitions $end
$comment Show the parameter values. $end
$dumpall
b100 &
$end
#0
$dumpvars
b0 (
b0 '
x%
0$
0#
0"
x!
$end
#10000
0!
1#
0%
#20000
0#
1%
#30000
1#
#40000
0#
#50000
1#
#60000
0#
#70000
1#
#80000
0#
#90000
1#
#100000
0#
#110000
1#
#120000
0#
1$
#130000
b1 (
1#
#140000
0#
#150000
b11 (
1#
#160000
0#
#170000
1"
b111 (
1#
#180000
0#
#190000
0"
b1111 (
1#
#200000
0#
#210000
1!
1#
#220000
0#
#230000
1#
#240000
0#
#250000
1#
#260000
0#
#270000
1#
#280000
0#
#290000
1#
#300000
0#
#310000
1#
#320000
0#
#330000
1#
#340000
0#
#350000
1#
#360000
0#
#370000
1#
#380000
0#
#390000
1#
#400000
0#
#410000
1#
#420000
0#
#430000
1#
#440000
0#
#450000
1#
#460000
0#
#470000
1#
#480000
0#
#490000
1#
#500000
0#
#510000
1#
#520000
0#
#530000
1#
#540000
0#
#550000
1#
#560000
0#
#570000
1#
#580000
0#
#590000
1#
#600000
0#
#610000
1#
#620000
0#
0$
#630000
b1110 (
1#
#640000
0#
#650000
0!
b1100 (
1#
#660000
0#
#670000
b1000 (
1#
#680000
0#
#690000
b0 (
1#
