src/sev_seg_m.v
module sev_seg_m #(
    parameter CN = 20
)(
    input clk,rst,
    input [15:0] reg_seg,
    output reg [7:0] SEG,
    output reg [3:0] AN
);

reg [3:0]sev0;
reg [3:0]sev1;
reg [3:0]sev2;
reg [3:0]sev3;

reg [CN - 1 : 0] count = 0;

reg [7:0] text0 = 0;
reg [7:0] text1 = 0;
reg [7:0] text2 = 0;
reg [7:0] text3 = 0;

always @(posedge clk or negedge rst) begin
    if (~rst) begin
        sev0 <= 0;
        sev1 <= 0;
        sev2 <= 0;
        sev3 <= 0;

        count <= 0;
    end 
    
    else begin
        sev0 <= reg_seg[3:0];
        sev1 <= reg_seg[7:4];
        sev2 <= reg_seg[11:8];
        sev3 <= reg_seg[15:12];

        count <= count + 1;        
    end
    
end
always @(posedge clk) begin
    
case (count[CN-1:CN-2])
    2'b00:begin
        SEG[7:0]<= text0;
        AN[3:0] <= 4'b1110;
    end
    2'b01:begin
        AN[3:0] <= 4'b1101;
        SEG[7:0]<= text1;
    end
    2'b10:begin
        AN[3:0] <= 4'b1011;
        SEG[7:0]<= text2;
    end
    2'b11:begin
        SEG[7:0]<= text3;
        AN[3:0] <= 4'b0111;
    end
endcase

case (sev0)
    4'b0000: begin
        text0 <= 8'b00000011;  // было 11000000
    end
    4'b0001: begin
        text0 <= 8'b10011111;  // было 11111100
    end
    4'b0010: begin   
        text0 <= 8'b00100101;  // было 10100100
    end
    4'b0011: begin   
        text0 <= 8'b00001101;  // было 10110000
    end
    4'b0100: begin   
        text0 <= 8'b10011001;  // было 10011001 (симметричное)
    end
    4'b0101: begin   
        text0 <= 8'b01001001;  // было 10010010
    end
    4'b0110: begin   
        text0 <= 8'b01000001;  // было 10000010
    end
    4'b0111: begin   
        text0 <= 8'b01110011;  // было 11001110
    end
    4'b1000: begin   
        text0 <= 8'b00000001;  // было 10000000
    end
    4'b1001: begin   
        text0 <= 8'b00001001;  // было 10010000
    end
    4'b1010: begin   
        text0 <= 8'b00010001;  // было 10001000
    end
    4'b1011: begin   
        text0 <= 8'b11000001;  // было 10000011
    end
    4'b1100: begin   
        text0 <= 8'b01100011;  // было 11000110
    end
    4'b1101: begin   
        text0 <= 8'b10000101;  // было 10100001
    end
    4'b1110: begin   
        text0 <= 8'b01100001;  // было 10000110
    end
    4'b1111: begin   
        text0 <= 8'b01110001;  // было 10001110
    end
endcase


case (sev1)
    4'b0000:begin
        text1 <= 8'b00000011;
    end
    4'b0001: begin
        text1 <= 8'b10011111;
    end
    4'b0010: begin   
       text1 <= 8'b00100101;
    end
    4'b0011: begin   
       text1 <= 8'b00001101;
    end
    4'b0100: begin   
       text1 <= 8'b10011001;
    end
    4'b0101: begin   
       text1 <= 8'b01001001;
    end
    4'b0110: begin   
       text1 <= 8'b01000001;
    end
    4'b0111: begin   
       text1 <= 8'b01110011;
    end
    4'b1000: begin   
       text1 <= 8'b00000001;
    end
    4'b1001: begin   
       text1 <= 8'b00001001;
    end
    4'b1010: begin   
       text1 <= 8'b00010001;
    end
    4'b1011: begin   
       text1 <= 8'b11000001;
    end
    4'b1100: begin   
       text1 <= 8'b01100011;
    end
    4'b1101: begin   
       text1 <= 8'b10000101;
    end
    4'b1110: begin   
       text1 <= 8'b01100001;
    end
    4'b1111: begin   
       text1 <= 8'b01110001;
    end
endcase

case (sev2)
    4'b0000:begin
        text2 <= 8'b00000011;
    end
    4'b0001: begin
        text2 <= 8'b10011111;
    end
    4'b0010: begin   
       text2 <= 8'b00100101;
    end
    4'b0011: begin   
       text2 <= 8'b00001101;
    end
    4'b0100: begin   
       text2 <= 8'b10011001;
    end
    4'b0101: begin   
       text2 <= 8'b01001001;
    end
    4'b0110: begin   
       text2 <= 8'b01000001;
    end
    4'b0111: begin   
       text2 <= 8'b01110011;
    end
    4'b1000: begin   
       text2 <= 8'b00000001;
    end
    4'b1001: begin   
       text2 <= 8'b00001001;
    end
    4'b1010: begin   
       text2 <= 8'b00010001;
    end
    4'b1011: begin   
       text2 <= 8'b11000001;
    end
    4'b1100: begin   
       text2 <= 8'b01100011;
    end
    4'b1101: begin   
       text2 <= 8'b10000101;
    end
    4'b1110: begin   
       text2 <= 8'b01100001;
    end
    4'b1111: begin   
       text2 <= 8'b01110001;
    end
endcase

case (sev3)
    4'b0000:begin
        text3 <= 8'b00000011;
    end
    4'b0001: begin
        text3 <= 8'b10011111;
    end
    4'b0010: begin   
       text3 <= 8'b00100101;
    end
    4'b0011: begin   
       text3 <= 8'b00001101;
    end
    4'b0100: begin   
       text3 <= 8'b10011001;
    end
    4'b0101: begin   
       text3 <= 8'b01001001;
    end
    4'b0110: begin   
       text3 <= 8'b01000001;
    end
    4'b0111: begin   
       text3 <= 8'b01110011;
    end
    4'b1000: begin   
       text3 <= 8'b00000001;
    end
    4'b1001: begin   
       text3 <= 8'b00001001;
    end
    4'b1010: begin   
       text3 <= 8'b00010001;
    end
    4'b1011: begin   
       text3 <= 8'b11000001;
    end
    4'b1100: begin   
       text3 <= 8'b01100011;
    end
    4'b1101: begin   
       text3 <= 8'b10000101;
    end
    4'b1110: begin   
       text3 <= 8'b01100001;
    end
    4'b1111: begin   
       text3 <= 8'b01110001;
    end
endcase
end
    
endmodule

src/tb_sev_seg_m.v
`timescale 1ns / 1ps

module tb_sev_seg_m();

reg clk = 0;
reg rst = 1;
reg [15:0] data_in = 0;
wire [7:0] SEG;
wire [3:0] AN;

always #10 begin
    clk <= ~clk;
end

sev_seg_m uut(
    .clk(clk),
    .rst(rst),
    .reg_seg(data_in),
    .SEG(SEG),
    .AN(AN)
);

initial begin
    $dumpfile("tb_sev_seg_m.vcd");
    $dumpvars(0, tb_sev_seg_m);
#10;
rst = 0;
#10;
data_in <=16'h3210;
rst = 1;
#1000;
$finish;
end


    
endmodule

tb_sev_seg_m.vcd
$date
	Thu Mar 05 13:23:59 2026
$end
$version
	Icarus Verilog
$end
$timescale
	1s
$end
$scope module tb_sev_seg_m $end
$var wire 8 ! SEG [7:0] $end
$var wire 4 " AN [3:0] $end
$var reg 1 # clk $end
$var reg 16 $ data_in [15:0] $end
$var reg 1 % rst $end
$scope module uut $end
$var wire 1 # clk $end
$var wire 16 & reg_seg [15:0] $end
$var wire 1 % rst $end
$var parameter 32 ' CN $end
$var reg 4 ( AN [3:0] $end
$var reg 8 ) SEG [7:0] $end
$var reg 4 * count [3:0] $end
$var reg 4 + sev0 [3:0] $end
$var reg 4 , sev1 [3:0] $end
$var reg 4 - sev2 [3:0] $end
$var reg 4 . sev3 [3:0] $end
$var reg 8 / text0 [7:0] $end
$var reg 8 0 text1 [7:0] $end
$var reg 8 1 text2 [7:0] $end
$var reg 8 2 text3 [7:0] $end
$upscope $end
$upscope $end
$enddefinitions $end
$comment Show the parameter values. $end
$dumpall
b100 '
$end
#0
$dumpvars
b0 2
b0 1
b0 0
b0 /
bx .
bx -
bx ,
bx +
b0 *
bx )
bx (
b0 &
1%
b0 $
0#
bx "
bx !
$end
#10
b111111 2
b111111 1
b111111 0
b111111 /
b1 "
b1 (
b0 !
b0 )
b0 .
b0 -
b0 ,
b0 +
1#
0%
#20
b11001000010000 $
b11001000010000 &
0#
1%
#30
b111111 !
b111111 )
b1 *
b11 .
b10 -
b1 ,
1#
#40
0#
#50
b1001111 2
b1011011 1
b11 0
b10 *
1#
#60
0#
#70
b11 *
1#
#80
0#
#90
b100 *
1#
#100
0#
#110
b11 !
b11 )
b10 "
b10 (
b101 *
1#
#120
0#
#130
b110 *
1#
#140
0#
#150
b111 *
1#
#160
0#
#170
b1000 *
1#
#180
0#
#190
b1011011 !
b1011011 )
b100 "
b100 (
b1001 *
1#
#200
0#
#210
b1010 *
1#
#220
0#
#230
b1011 *
1#
#240
0#
#250
b1100 *
1#
#260
0#
#270
b1000 "
b1000 (
b1001111 !
b1001111 )
b1101 *
1#
#280
0#
#290
b1110 *
1#
#300
0#
#310
b1111 *
1#
#320
0#
#330
b0 *
1#
#340
0#
#350
b1 "
b1 (
b111111 !
b111111 )
b1 *
1#
#360
0#
#370
b10 *
1#
#380
0#
#390
b11 *
1#
#400
0#
#410
b100 *
1#
#420
0#
#430
b11 !
b11 )
b10 "
b10 (
b101 *
1#
#440
0#
#450
b110 *
1#
#460
0#
#470
b111 *
1#
#480
0#
#490
b1000 *
1#
#500
0#
#510
b1011011 !
b1011011 )
b100 "
b100 (
b1001 *
1#
#520
0#
#530
b1010 *
1#
#540
0#
#550
b1011 *
1#
#560
0#
#570
b1100 *
1#
#580
0#
#590
b1000 "
b1000 (
b1001111 !
b1001111 )
b1101 *
1#
#600
0#
#610
b1110 *
1#
#620
0#
#630
b1111 *
1#
#640
0#
#650
b0 *
1#
#660
0#
#670
b1 "
b1 (
b111111 !
b111111 )
b1 *
1#
#680
0#
#690
b10 *
1#
#700
0#
#710
b11 *
1#
#720
0#
#730
b100 *
1#
#740
0#
#750
b11 !
b11 )
b10 "
b10 (
b101 *
1#
#760
0#
#770
b110 *
1#
#780
0#
#790
b111 *
1#
#800
0#
#810
b1000 *
1#
#820
0#
#830
b1011011 !
b1011011 )
b100 "
b100 (
b1001 *
1#
#840
0#
#850
b1010 *
1#
#860
0#
#870
b1011 *
1#
#880
0#
#890
b1100 *
1#
#900
0#
#910
b1000 "
b1000 (
b1001111 !
b1001111 )
b1101 *
1#
#920
0#
#930
b1110 *
1#
#940
0#
#950
b1111 *
1#
#960
0#
#970
b0 *
1#
#980
0#
#990
b1 "
b1 (
b111111 !
b111111 )
b1 *
1#
#1000
0#
#1010
b10 *
1#
